wagtail_nav_menus/__init__.py
wagtail_nav_menus/apps.py
wagtail_nav_menus/defaults.py
wagtail_nav_menus/loading.py
wagtail_nav_menus/locale/es/LC_MESSAGES/django.mo
wagtail_nav_menus/locale/es/LC_MESSAGES/django.po
wagtail_nav_menus/migrations/0001_initial.py
wagtail_nav_menus/migrations/0002_auto_20190911_1745.py
wagtail_nav_menus/migrations/0003_auto_20191111_1655.py
wagtail_nav_menus/migrations/0004_alter_navmenu_menu.py
wagtail_nav_menus/migrations/__init__.py
wagtail_nav_menus/models.py
wagtail_nav_menus/py.typed
wagtail_nav_menus/serializers.py
wagtail_nav_menus/templates/nav_menus/get_url.html
wagtail_nav_menus/templates/nav_menus/menu_link.html
wagtail_nav_menus/templates/nav_menus/nav_category.html
wagtail_nav_menus/templates/nav_menus/tags/menu.html
wagtail_nav_menus/templatetags/__init__.py
wagtail_nav_menus/templatetags/nav_menu_tags.py
wagtail_nav_menus/tests.py
wagtail_nav_menus/utils.py
wagtail_nav_menus/viewsets.py
wagtail_nav_menus/wagtail_hooks.py
wagtail_nav_menus-3.13.2.dist-info/LICENSE
wagtail_nav_menus-3.13.2.dist-info/METADATA
wagtail_nav_menus-3.13.2.dist-info/WHEEL
wagtail_nav_menus-3.13.2.dist-info/RECORD
