Metadata-Version: 2.3
Name: wagtail-nav-menus
Version: 3.13.2
Summary: Wagtail Nav Menus is a app to provide highly customizable menus in wagtail by leveraging StreamFields.
License: ISC
Author: thelab
Author-email: thelabdev@thelab.co
Requires-Python: >=3.11,<4.0
Classifier: License :: OSI Approved
Classifier: Programming Language :: Python :: 3
Classifier: Programming Language :: Python :: 3.11
Classifier: Programming Language :: Python :: 3.12
Classifier: Programming Language :: Python :: 3.13
Requires-Dist: wagtail (>=6.3)
Requires-Dist: wagtail-modeladmin (>=2.1.0,<3.0.0)
Project-URL: Homepage, https://gitlab.com/thelabnyc/wagtail-nav-menus
Project-URL: Repository, https://gitlab.com/thelabnyc/wagtail-nav-menus
